cal.py
setup.py
bsd_calendar.egg-info/PKG-INFO
bsd_calendar.egg-info/SOURCES.txt
bsd_calendar.egg-info/dependency_links.txt
bsd_calendar.egg-info/entry_points.txt
bsd_calendar.egg-info/top_level.txt