Metadata-Version: 1.1
Name: bsd-calendar
Version: 0.0.0
Summary: BSD calendar reimplementation
Home-page: https://github.com/xi/calendar
Author: Tobias Bengfort
Author-email: tobias.bengfort@posteo.de
License: BSD
Platform: UNKNOWN
Classifier: Development Status :: 3 - Alpha
Classifier: Environment :: Console
Classifier: Intended Audience :: End Users/Desktop
Classifier: Operating System :: OS Independent
Classifier: Programming Language :: Python :: 3.4
Classifier: License :: OSI Approved :: BSD License
Classifier: Topic :: Utilities
